README.txt
distribute_setup.py
setup.py
robutils/ExternalCmd.py
robutils/Instance.py
robutils/LICENSE.txt
robutils/Message.py
robutils/Progress.py
robutils/__init__.py
robutils/version.py
robutils.egg-info/PKG-INFO
robutils.egg-info/SOURCES.txt
robutils.egg-info/dependency_links.txt
robutils.egg-info/requires.txt
robutils.egg-info/top_level.txt