Metadata-Version: 1.0
Name: robutils
Version: 1.0.0
Summary: Convenience classes for CLI Python applications.
Home-page: http://code.google.com/p/robutils/
Author: Robpol86
Author-email: robpol86@robpol86.com
License: MIT
Platform: UNKNOWN
